Metadata-Version: 2.1
Name: fitsImageProcess
Version: 0.6.0
Summary: A package for processing FITS images
Home-page: https://pypi.org/project/fitsImageProcess/0.4.0/
Author: Matthieu Musy
Author-email: matthieu.musy@ensta-bretagne.org
License: MIT
Requires-Dist: numpy
Requires-Dist: astropy
Requires-Dist: matplotlib
Requires-Dist: photutils
Requires-Dist: sep
Requires-Dist: astroquery
Requires-Dist: numba
Requires-Dist: reproject
Requires-Dist: scipy
Requires-Dist: setuptools
Requires-Dist: opencv-python
Requires-Dist: cmastro
Requires-Dist: scikit-image
